f1_22_telemetry/__init__.py
f1_22_telemetry/appendices.py
f1_22_telemetry/listener.py
f1_22_telemetry/main.py
f1_22_telemetry/packets.py
f1_22_telemetry-0.1.2.dist-info/METADATA
f1_22_telemetry-0.1.2.dist-info/WHEEL
f1_22_telemetry-0.1.2.dist-info/licenses/LICENSE
f1_22_telemetry-0.1.2.dist-info/RECORD
