Metadata-Version: 2.1
Name: f1-22-telemetry
Version: 0.1.2
Summary: Decode F1 22 telemetry data.
Project-URL: Homepage, https://github.com/chrishannam/f1-22-telemetry
Project-URL: Bug Tracker, https://github.com/chrishannam/f1-22-telemetry/issues
Author-email: Chris Hannam <ch@chrishannam.co.uk>
License: MIT License
License-File: LICENSE
Classifier: License :: OSI Approved :: MIT License
Classifier: Operating System :: OS Independent
Classifier: Programming Language :: Python :: 3
Requires-Python: >=3.7
